{
  "main": {
    "id": "f08cf950372e8b97",
    "type": "split",
    "children": [
      {
        "id": "47cc769a2da59652",
        "type": "tabs",
        "children": [
          {
            "id": "9918f3c6a5ae42c1",
            "type": "leaf",
            "state": {
              "type": "image",
              "state": {
                "file": "assets/attachments/_processed/Coffee Cup Planter/IMG_20200704_095624.webp"
              },
              "icon": "lucide-image",
              "title": "IMG_20200704_095624"
            }
          },
          {
            "id": "41191577799f619b",
            "type": "leaf",
            "state": {
              "type": "image",
              "state": {
                "file": "assets/attachments/_processed/Coffee Cup Wall Art/20250521_120955.webp"
              },
              "icon": "lucide-image",
              "title": "20250521_120955"
            }
          },
          {
            "id": "89503fe7ec7415d3",
            "type": "leaf",
            "state": {
              "type": "image",
              "state": {
                "file": "assets/attachments/_processed/Coffee Cup Wall Art/20250521_120955.webp"
              },
              "icon": "lucide-image",
              "title": "20250521_120955"
            }
          },
          {
            "id": "543291309820253c",
            "type": "leaf",
            "state": {
              "type": "image",
              "state": {
                "file": "assets/attachments/_processed/Coffee Cup Wall Art/coffee_cup_wall_art_2024-Jan-24_06-41-44AM-000_CustomizedView21556000476.webp"
              },
              "icon": "lucide-image",
              "title": "coffee_cup_wall_art_2024-Jan-24_06-41-44AM-000_CustomizedView21556000476"
            }
          },
          {
            "id": "9718886fc34cfeed",
            "type": "leaf",
            "state": {
              "type": "markdown",
              "state": {
                "file": "projects/Filament Drier.md",
                "mode": "source",
                "source": false
              },
              "icon": "lucide-file",
              "title": "Filament Drier"
            }
          }
        ],
        "currentTab": 4
      }
    ],
    "direction": "vertical"
  },
  "left": {
    "id": "b56b65c12586a911",
    "type": "split",
    "children": [
      {
        "id": "8da22e9bbd47b623",
        "type": "tabs",
        "children": [
          {
            "id": "7c7519ae8af5b2ee",
            "type": "leaf",
            "state": {
              "type": "file-explorer",
              "state": {
                "sortOrder": "alphabetical",
                "autoReveal": false
              },
              "icon": "lucide-folder-closed",
              "title": "Files"
            }
          },
          {
            "id": "cb3f62f533589469",
            "type": "leaf",
            "state": {
              "type": "search",
              "state": {
                "query": "",
                "matchingCase": false,
                "explainSearch": false,
                "collapseAll": false,
                "extraContext": false,
                "sortOrder": "alphabetical"
              },
              "icon": "lucide-search",
              "title": "Search"
            }
          },
          {
            "id": "96c05d5a7c0007f9",
            "type": "leaf",
            "state": {
              "type": "bookmarks",
              "state": {},
              "icon": "lucide-bookmark",
              "title": "Bookmarks"
            }
          }
        ]
      }
    ],
    "direction": "horizontal",
    "width": 693.5085258483887
  },
  "right": {
    "id": "c0dfaf813882b78a",
    "type": "split",
    "children": [
      {
        "id": "8411a21f0abe4b81",
        "type": "tabs",
        "children": [
          {
            "id": "68fac62d444175a2",
            "type": "leaf",
            "state": {
              "type": "backlink",
              "state": {
                "collapseAll": false,
                "extraContext": false,
                "sortOrder": "alphabetical",
                "showSearch": false,
                "searchQuery": "",
                "backlinkCollapsed": false,
                "unlinkedCollapsed": true
              },
              "icon": "links-coming-in",
              "title": "Backlinks"
            }
          },
          {
            "id": "7a2028871fef13ec",
            "type": "leaf",
            "state": {
              "type": "outgoing-link",
              "state": {
                "linksCollapsed": false,
                "unlinkedCollapsed": true
              },
              "icon": "links-going-out",
              "title": "Outgoing links"
            }
          },
          {
            "id": "3ed3b5c93bfd9ed0",
            "type": "leaf",
            "state": {
              "type": "outline",
              "state": {
                "file": "projects/Filament Drier.md",
                "followCursor": false,
                "showSearch": false,
                "searchQuery": ""
              },
              "icon": "lucide-list",
              "title": "Outline of Filament Drier"
            }
          },
          {
            "id": "34eb308f1f76385a",
            "type": "leaf",
            "state": {
              "type": "advanced-tables-toolbar",
              "state": {},
              "icon": "spreadsheet",
              "title": "Advanced Tables"
            }
          }
        ],
        "currentTab": 3
      }
    ],
    "direction": "horizontal",
    "width": 568.5,
    "collapsed": true
  },
  "left-ribbon": {
    "hiddenItems": {
      "command-palette:Open command palette": false,
      "bases:Create new base": false,
      "switcher:Open quick switcher": false,
      "graph:Open graph view": false,
      "canvas:Create new canvas": false,
      "daily-notes:Open today's daily note": false,
      "templates:Insert template": false,
      "table-editor-obsidian:Advanced Tables Toolbar": false,
      "publish:Publish changes...": false
    }
  },
  "active": "9718886fc34cfeed",
  "lastOpenFiles": [
    "assets/attachments/_processed/_processed/Filament Drier/IMG_20220812_150824-large.webp",
    "assets/attachments/_processed/_processed/Filament Drier/IMG_20220812_150824-medium.webp",
    "assets/attachments/_processed/_processed/Filament Drier/IMG_20220812_150824-small.webp",
    "assets/attachments/_processed/_processed/Filament Drier",
    "assets/attachments/_processed/_processed/DSOX Cover/20250521_121400-large.webp",
    "assets/attachments/_processed/_processed/DSOX Cover/20250521_121400-medium.webp",
    "assets/attachments/_processed/_processed/DSOX Cover/20250521_121400-small.webp",
    "assets/attachments/_processed/_processed/DSOX Cover",
    "assets/attachments/_processed/_processed/Desk Phone Holder Charger/20250423_183047-large.webp",
    "assets/attachments/_processed/_processed/Desk Phone Holder Charger/20250423_183047-medium.webp",
    "assets/attachments/_processed/_processed/Desk Phone Holder Charger/20250423_183047-small.webp",
    "assets/attachments/_processed/_processed/Desk Phone Holder Charger",
    "assets/attachments/_processed/_processed/Desk Clamp/20250521_121456-large.webp",
    "assets/attachments/_processed/_processed/Desk Clamp/20250521_121456-medium.webp",
    "assets/attachments/_processed/_processed/Desk Clamp",
    "projects/Desk Clamp.md",
    "projects/Desk Phone Holder Charger.md",
    "projects/DSOX Cover.md",
    "projects/Filament Drier.md",
    "assets/attachments/DSOX Cover/~0250515_095350.tmp",
    "assets/attachments/DSOX Cover/~0250515_095343.tmp",
    "assets/attachments/Desk Phone Holder Charger/~0250423_183102.tmp",
    "assets/attachments/Desk Phone Holder Charger/~0250423_183047.tmp",
    "projects/_Untitled.md",
    "assets/attachments/Desk Clamp/~0250428_163820.tmp",
    "projects/Coffee Cup Wall Art.md",
    "projects/Coffee Cup Planter.md",
    "assets/attachments/_processed/_processed/Travel Matcha Set",
    "projects/_WIP/Leather Wallet w Notepad.md",
    "projects/_WIP/Travel Matcha Set.md",
    "projects/Work Examples.md",
    "projects/_WIP/Simplicity.md",
    "projects/_WIP/Splitbox.md",
    "projects/_WIP/Guitar.md",
    "projects/2026-02-11.md",
    "assets/attachments/_processed/Splitbox/89cce57c-0022-448e-a5fb-296175ec8599-large.webp.sidecar.md",
    "assets/attachments/_processed/Splitbox/89cce57c-0022-448e-a5fb-296175ec8599-medium.webp.sidecar.md",
    "assets/attachments/_processed/Splitbox/89cce57c-0022-448e-a5fb-296175ec8599-small.webp.sidecar.md",
    "assets/temp/Mountain128-medium.webp.sidecar.md",
    "assets/temp/Mountain128-large.webp.sidecar.md",
    "assets/temp/20231221_092618-small.webp.sidecar.md",
    "assets/temp/20231221_092618-medium.webp.sidecar.md",
    "assets/temp/20231221_092618-large.webp.sidecar.md",
    "assets/temp/20231221_092707-small.webp.sidecar.md",
    "assets/temp/20231221_092707-medium.webp.sidecar.md",
    "assets/temp/20231221_092707-large.webp.sidecar.md"
  ]
}